adaptive_floor/__init__.py
adaptive_floor/main.py
adaptive_floor-0.1.6.dist-info/LICENSE
adaptive_floor-0.1.6.dist-info/METADATA
adaptive_floor-0.1.6.dist-info/WHEEL
adaptive_floor-0.1.6.dist-info/top_level.txt
adaptive_floor-0.1.6.dist-info/RECORD
