Metadata-Version: 2.2
Name: adaptive_floor
Version: 0.1.6
Summary: A lightweight Python library for precise number flooring and formatting. Includes adaptive decimal precision based on the fractional magnitude.
Author-email: tnam0x <namtran4194@gmail.com>
License: GPL-3.0-only
Project-URL: Homepage, https://github.com/tnam0x/adaptive_floor
Classifier: Programming Language :: Python :: 3
Classifier: License :: OSI Approved :: GNU General Public License v3 (GPLv3)
Classifier: Operating System :: OS Independent
Requires-Python: >=3.6
License-File: LICENSE
